instinct_py_nodes/__init__.py
instinct_py_nodes/node.py
instinct_py_nodes-0.1.5.dist-info/LICENSE
instinct_py_nodes-0.1.5.dist-info/METADATA
instinct_py_nodes-0.1.5.dist-info/WHEEL
instinct_py_nodes-0.1.5.dist-info/top_level.txt
instinct_py_nodes-0.1.5.dist-info/RECORD
