Metadata-Version: 2.1
Name: instinct_py_nodes
Version: 0.1.5
Summary: A Python package for creating distributed nodes using ZeroMQ
Home-page: https://github.com/yourusername/sw-instinct-py-nodes
Author: Nexstem
Author-email: developers@nexstem.ai
Classifier: Programming Language :: Python :: 3
Classifier: License :: OSI Approved :: MIT License
Classifier: Operating System :: OS Independent
Requires-Python: >=3.6
License-File: LICENSE
Requires-Dist: pyzmq >=0.0.0
